general_insurance_data_model/__init__.py
general_insurance_data_model/generators.py
general_insurance_data_model-0.0.6.dist-info/LICENSE.txt
general_insurance_data_model-0.0.6.dist-info/METADATA
general_insurance_data_model-0.0.6.dist-info/WHEEL
general_insurance_data_model-0.0.6.dist-info/top_level.txt
general_insurance_data_model-0.0.6.dist-info/RECORD
