Metadata-Version: 2.1
Name: general_insurance_data_model
Version: 0.0.6
Summary: Generate insurance data for testing and demonstrations
Author-email: Peter Dyson <peter@dysonmail.me>
License: GNU GENERAL PUBLIC LICENSE
Keywords: actuarial,insurance,reserving,pricing
License-File: LICENSE.txt
Requires-Dist: pandas>=1.5.0
Requires-Dist: numpy==1.26.4
